Metadata-Version: 2.1
Name: phuong-distributions
Version: 0.1
Summary: Gaussian distributions
